odoo/addons/ssi_l10n_id_taxform/README.rst
odoo/addons/ssi_l10n_id_taxform/__init__.py
odoo/addons/ssi_l10n_id_taxform/__manifest__.py
odoo/addons/ssi_l10n_id_taxform/menu.xml
odoo/addons/ssi_l10n_id_taxform/data/taxform_objek_pajak_data.xml
odoo/addons/ssi_l10n_id_taxform/models/__init__.py
odoo/addons/ssi_l10n_id_taxform/models/res_company.py
odoo/addons/ssi_l10n_id_taxform/models/res_config_settings.py
odoo/addons/ssi_l10n_id_taxform/models/res_partner.py
odoo/addons/ssi_l10n_id_taxform/models/tax_period.py
odoo/addons/ssi_l10n_id_taxform/models/taxform_objek_pajak.py
odoo/addons/ssi_l10n_id_taxform/security/ir.model.access.csv
odoo/addons/ssi_l10n_id_taxform/security/ir_module_category_data.xml
odoo/addons/ssi_l10n_id_taxform/security/res_group_data.xml
odoo/addons/ssi_l10n_id_taxform/static/description/icon.png
odoo/addons/ssi_l10n_id_taxform/views/res_config_settings_views.xml
odoo/addons/ssi_l10n_id_taxform/views/res_partner_views.xml
odoo/addons/ssi_l10n_id_taxform/views/tax_period_views.xml
odoo/addons/ssi_l10n_id_taxform/views/taxform_objek_pajak_views.xml
odoo14_addon_ssi_l10n_id_taxform-14.0.1.5.0.dist-info/METADATA
odoo14_addon_ssi_l10n_id_taxform-14.0.1.5.0.dist-info/WHEEL
odoo14_addon_ssi_l10n_id_taxform-14.0.1.5.0.dist-info/top_level.txt
odoo14_addon_ssi_l10n_id_taxform-14.0.1.5.0.dist-info/RECORD
